mtcli_volume/__init__.py
mtcli_volume/cli.py
mtcli_volume/conf.py
mtcli_volume/controller.py
mtcli_volume/model.py
mtcli_volume/plugin.py
mtcli_volume/view.py
mtcli_volume-2.4.2.dist-info/entry_points.txt
mtcli_volume-2.4.2.dist-info/licenses/LICENSE
mtcli_volume-2.4.2.dist-info/METADATA
mtcli_volume-2.4.2.dist-info/WHEEL
mtcli_volume-2.4.2.dist-info/RECORD
